easyquotation/__init__.py
easyquotation/api.py
easyquotation/basequotation.py
easyquotation/boc.py
easyquotation/daykline.py
easyquotation/helpers.py
easyquotation/hkquote.py
easyquotation/jsl.py
easyquotation/sina.py
easyquotation/stock_codes.conf
easyquotation/tencent.py
easyquotation/timekline.py
easyquotation-0.7.7.dist-info/LICENSE
easyquotation-0.7.7.dist-info/METADATA
easyquotation-0.7.7.dist-info/WHEEL
easyquotation-0.7.7.dist-info/top_level.txt
easyquotation-0.7.7.dist-info/RECORD
