Metadata-Version: 2.1
Name: easyquotation
Version: 0.7.7
Summary: A utility for Fetch China Stock Info
Home-page: https://github.com/shidenggui/easyquotation
Author: shidenggui
Author-email: longlyshidenggui@gmail.com
License: BSD
Keywords: China stock trade
Classifier: Development Status :: 4 - Beta
Classifier: Programming Language :: Python :: 3.5
Classifier: License :: OSI Approved :: BSD License
License-File: LICENSE
Requires-Dist: requests
Requires-Dist: six
Requires-Dist: easyutils
